broccli/__about__.py
broccli/__init__.py
broccli/app.py
broccli/entry_points.py
broccli-0.0.2.dist-info/METADATA
broccli-0.0.2.dist-info/WHEEL
broccli-0.0.2.dist-info/entry_points.txt
broccli-0.0.2.dist-info/licenses/LICENSE.txt
broccli-0.0.2.dist-info/RECORD
